Workbook

Sheet 帳戶名單
A1: 帳戶名稱 | B1: 初始金額(台幣) | C1: 目前餘額
A2: 👛錢包 | B2: 3000 | C2: =B2 + SUMIFS('流水帳'!H:H, '流水帳'!F:F, A2, '流水帳'!C:C, "收入") - SUMIFS('流水帳'!H:H, '流水帳'!F:F, A2, '流水帳'!C:C, "支出") -> 4850
A3: 🎫悠遊卡 / ICOCA | B3: 1000 | C3: =B3 + SUMIFS('流水帳'!H:H, '流水帳'!F:F, A3, '流水帳'!C:C, "收入") - SUMIFS('流水帳'!H:H, '流水帳'!F:F, A3, '流水帳'!C:C, "支出") -> 1000
A4: 街口帳戶 | B4: 500 | C4: =B4 + SUMIFS('流水帳'!H:H, '流水帳'!F:F, A4, '流水帳'!C:C, "收入") - SUMIFS('流水帳'!H:H, '流水帳'!F:F, A4, '流水帳'!C:C, "支出") -> 500
A5: 🏦玉山生活 | B5: 50000 | C5: =B5 + SUMIFS('流水帳'!H:H, '流水帳'!F:F, A5, '流水帳'!C:C, "收入") - SUMIFS('流水帳'!H:H, '流水帳'!F:F, A5, '流水帳'!C:C, "支出") -> 93000
A6: 🏦國泰新生活 | B6: 30000 | C6: =B6 + SUMIFS('流水帳'!H:H, '流水帳'!F:F, A6, '流水帳'!C:C, "收入") - SUMIFS('流水帳'!H:H, '流水帳'!F:F, A6, '流水帳'!C:C, "支出") -> 30000
A7: 🏦富邦數位帳戶 | B7: 20000 | C7: =B7 + SUMIFS('流水帳'!H:H, '流水帳'!F:F, A7, '流水帳'!C:C, "收入") - SUMIFS('流水帳'!H:H, '流水帳'!F:F, A7, '流水帳'!C:C, "支出") -> 20000
A8: 🏦郵局 | B8: 15000 | C8: =B8 + SUMIFS('流水帳'!H:H, '流水帳'!F:F, A8, '流水帳'!C:C, "收入") - SUMIFS('流水帳'!H:H, '流水帳'!F:F, A8, '流水帳'!C:C, "支出") -> 14400
A9: 💳國泰cube | B9: 0 | C9: =B9 + SUMIFS('流水帳'!H:H, '流水帳'!F:F, A9, '流水帳'!C:C, "收入") - SUMIFS('流水帳'!H:H, '流水帳'!F:F, A9, '流水帳'!C:C, "支出") -> 0
A10: 💳玉山熊熊 | B10: 0 | C10: =B10 + SUMIFS('流水帳'!H:H, '流水帳'!F:F, A10, '流水帳'!C:C, "收入") - SUMIFS('流水帳'!H:H, '流水帳'!F:F, A10, '流水帳'!C:C, "支出") -> 0
A11: 💳富邦J卡 | B11: 0 | C11: =B11 + SUMIFS('流水帳'!H:H, '流水帳'!F:F, A11, '流水帳'!C:C, "收入") - SUMIFS('流水帳'!H:H, '流水帳'!F:F, A11, '流水帳'!C:C, "支出") -> -450
A12: 🏦台企銀 | B12: 10000 | C12: =B12 + SUMIFS('流水帳'!H:H, '流水帳'!F:F, A12, '流水帳'!C:C, "收入") - SUMIFS('流水帳'!H:H, '流水帳'!F:F, A12, '流水帳'!C:C, "支出") -> 10000 | I12: 台幣總資產
A13: 🏦台灣銀行 (進修基金) | B13: 50000 | C13: =B13 + SUMIFS('流水帳'!H:H, '流水帳'!F:F, A13, '流水帳'!C:C, "收入") - SUMIFS('流水帳'!H:H, '流水帳'!F:F, A13, '流水帳'!C:C, "支出") -> 50000 | I13: =SUM(C2:C19) -> 553300
A14: 🏦永豐大戶 | B14: 20000 | C14: =B14 + SUMIFS('流水帳'!H:H, '流水帳'!F:F, A14, '流水帳'!C:C, "收入") - SUMIFS('流水帳'!H:H, '流水帳'!F:F, A14, '流水帳'!C:C, "支出") -> 20000
A15: ✈️專款基金 (出國旅遊) | B15: 30000 | C15: =B15 + SUMIFS('流水帳'!H:H, '流水帳'!F:F, A15, '流水帳'!C:C, "收入") - SUMIFS('流水帳'!H:H, '流水帳'!F:F, A15, '流水帳'!C:C, "支出") -> 30000 | I15: 美金總資產 | J15: 換算台幣
A16: 🏦聯邦NewNewBank | B16: 50000 | C16: =B16 + SUMIFS('流水帳'!H:H, '流水帳'!F:F, A16, '流水帳'!C:C, "收入") - SUMIFS('流水帳'!H:H, '流水帳'!F:F, A16, '流水帳'!C:C, "支出") -> 50000 | I16: =SUM(C22:C25) -> 5000 | J16: =IFERROR(__xludf.DUMMYFUNCTION("GOOGLEFINANCE(""CURRENCY:USDTWD"")*I16"),162500) -> 162500
A17: 🏦國泰台股交割戶 | B17: 20000 | C17: =B17 + SUMIFS('流水帳'!H:H, '流水帳'!F:F, A17, '流水帳'!C:C, "收入") - SUMIFS('流水帳'!H:H, '流水帳'!F:F, A17, '流水帳'!C:C, "支出") -> 20000
A18: 📈台股已投入成本 | B18: 250000 | C18: =B18 + SUMIFS('流水帳'!H:H, '流水帳'!F:F, A18, '流水帳'!C:C, "收入") - SUMIFS('流水帳'!H:H, '流水帳'!F:F, A18, '流水帳'!C:C, "支出") -> 250000 | I18: 現金總資產
A19: 🏦薪轉帳戶 | B19: 0 | C19: =B19 + SUMIFS('流水帳'!H:H, '流水帳'!F:F, A19, '流水帳'!C:C, "收入") - SUMIFS('流水帳'!H:H, '流水帳'!F:F, A19, '流水帳'!C:C, "支出") -> 0 | I19: =I13+J16 -> 715800
A21: 帳戶名稱 | B21: 初始金額(美金) | I21: 保底總資產 (預扣專款基金) | K21: 股票未實現淨利 (選填)
A22: Line Bank 美金 | B22: 500 | C22: =B22 + SUMIFS('流水帳'!H:H, '流水帳'!F:F, A22, '流水帳'!C:C, "收入") - SUMIFS('流水帳'!H:H, '流水帳'!F:F, A22, '流水帳'!C:C, "支出") -> 500 | I22: =I19-C15 -> 685800 | K22: 50000
A23: 國泰美金 | B23: 500 | C23: =B23 + SUMIFS('流水帳'!H:H, '流水帳'!F:F, A23, '流水帳'!C:C, "收入") - SUMIFS('流水帳'!H:H, '流水帳'!F:F, A23, '流水帳'!C:C, "支出") -> 500
A24: Firstrade 交割戶 | B24: 1000 | C24: =B24 + SUMIFS('流水帳'!H:H, '流水帳'!F:F, A24, '流水帳'!C:C, "收入") - SUMIFS('流水帳'!H:H, '流水帳'!F:F, A24, '流水帳'!C:C, "支出") -> 1000 | K24: 全部總資產
A25: 美股投入成本 | B25: 3000 | C25: =B25 + SUMIFS('流水帳'!H:H, '流水帳'!F:F, A25, '流水帳'!C:C, "收入") - SUMIFS('流水帳'!H:H, '流水帳'!F:F, A25, '流水帳'!C:C, "支出") -> 3000 | K25: =I19+K22 -> 765800
I27: 保底總資產存錢目標 說明： 1. 範例：希望一年存 20 萬，每月定期定額存 1.7 萬 2. 可依個人年度理財計畫自由調整下方各月目標（單位：萬）
I29: 時間 | J29: 資產目標 | K29: 備註
I30: 2026年1月底 | J30: 60
I31: 2026年2月底 | J31: 61.5 | K31: 範例：可記錄當月獎金或大筆支出備註
I32: 2026年3月底 | J32: 63
I33: 2026年4月底 | J33: 64.5
I34: 2026年5月底 | J34: 66
I35: 2026年6月底 | J35: 67.5
I36: 2026年7月底 | J36: 69
I37: 2026年8月底 | J37: 70.5
I38: 2026年9月底 | J38: 72
I39: 2026年10月底 | J39: 73.5
I40: 2026年11月底 | J40: 75
I41: 2026年12月底 | J41: 76.5

Sheet 預算進度
A1: ="今天是"&TEXT(NOW(), "yyyy年m月d日aaaa")&" 時間："&TEXT(NOW(), "hh:mm") -> 今天是2026年10月25日星期日 時間：08:42 | I1: 美金匯率 | J1: =IFERROR(__xludf.DUMMYFUNCTION("GOOGLEFINANCE(""CURRENCY:USDTWD"")"),32.585800000000006) -> 32.5858
I2: 日幣匯率 | J2: =IFERROR(__xludf.DUMMYFUNCTION("GOOGLEFINANCE(""CURRENCY:JPYTWD"")"),0.2077359) -> 0.2077359
A3: ="本月還剩餘 " & (EOMONTH(TODAY(),0)-TODAY()+1) & " 天" -> 本月還剩餘 7 天
A5: 當月一般預算 | B5: 當月一般性支出 | C5: 一般性支出比例 | D5: 剩餘的一般預算 | E5: 當月時間進度 | F5: 今日一般預算
A6: =15000 -> 15000 | B6: =SUMIFS('流水帳'!E:E, '流水帳'!B:B, "一般花費", '流水帳'!A:A, ">="&DATE(YEAR(TODAY()), MONTH(TODAY()), 1)) -> 750 | C6: =B6/A6 -> 0.05 | D6: =A6-B6 -> 14250 | E6: =DAY(TODAY()) / DAY(EOMONTH(TODAY(), 0)) -> 0.80645161 | F6: =G6 - SUMIFS('流水帳'!E:E, '流水帳'!B:B, "一般花費", '流水帳'!A:A, ">="&TODAY(), '流水帳'!A:A, "<"&TODAY()+1) -> 500 | G6: 500
A7: 當月其他類預算 | B7: 當月其他類支出 | C7: 其他類支出比例 | D7: 剩餘的其他類預算 | F7: 今日其他類預算
A8: =10000 -> 10000 | B8: =SUMIFS('流水帳'!E:E, '流水帳'!B:B, "特支費", '流水帳'!A:A, ">="&DATE(YEAR(TODAY()), MONTH(TODAY()), 1)) -> 450 | C8: =B8/A8 -> 0.045 | D8: =A8-B8 -> 9550 | F8: =G8 - SUMIFS('流水帳'!E:E, '流水帳'!B:B, "特支費", '流水帳'!A:A, TODAY()) -> 350 | G8: 350
A11: 藍色 (#4A90E2)：代表你目前的一般性支出。 灰色 (#E0E0E0)：代表本月時間進度（相對於支出）。
A13: =IFERROR(__xludf.DUMMYFUNCTION("SPARKLINE( { MIN(C6, DAY(TODAY())/DAY(EOMONTH(TODAY(),0))), 0.01, MAX(0, C6 - DAY(TODAY())/DAY(EOMONTH(TODAY(),0)) - 0.01), MAX(0, 1 - MAX(C6, DAY(TODAY())/DAY(EOMONTH(TODAY(),0) + 0.01))) }, { ""charttype"", ""bar""; ""m"&"ax"", 1; ""color1"", ""#4A90E2""; ""color2"", ""#FF0000""; ""color3"", ""#4A90E2""; ""color4"", ""#E0E0E0"" } )"),"")
A16: 橘色 (#F5A623)：代表你目前的其他類支出。
A18: =IFERROR(__xludf.DUMMYFUNCTION("SPARKLINE( { MIN(C8, DAY(TODAY())/DAY(EOMONTH(TODAY(),0))), 0.01, MAX(0, C8 - DAY(TODAY())/DAY(EOMONTH(TODAY(),0)) - 0.01), MAX(0, 1 - MAX(C8, DAY(TODAY())/DAY(EOMONTH(TODAY(),0) + 0.01))) }, { ""charttype"", ""bar""; ""m"&"ax"", 1; ""color1"", ""#F5A623""; ""color2"", ""#FF0000""; ""color3"", ""#F5A623""; ""color4"", ""#E0E0E0"" } )"),"")

Sheet 選單設定
A1: 預算分類 (A欄) | B1: 詳細項目 (B欄)
A2: 一般花費 | B2: 早餐
A3: 一般花費 | B3: 午餐
A4: 一般花費 | B4: 晚餐
A5: 一般花費 | B5: 飲料
A6: 一般花費 | B6: 咖啡
A7: 一般花費 | B7: 水果
A8: 一般花費 | B8: 零食/點心
A9: 一般花費 | B9: 交通
A10: 一般花費 | B10: 醫療
A11: 一般花費 | B11: 日用品
A12: 一般花費 | B12: 房租
... A97: ✈️出國旅遊專案 | B97: 人身保險
A98: ✈️出國旅遊專案
A99: ✈️出國旅遊專案

Sheet 流水帳
A1: 日期 | B1: 類別 | C1: 收支 | D1: 項目 | E1: 金額 | F1: 帳戶/路徑 | G1: 備註 | H1: H 原始金額 (必加) | I1: Column 9
A2: 46296 | B2: 收入 | C2: 收入 | D2: 10月薪資 (範例) | E2: 0 | F2: 🏦玉山生活 | G2: TWD 收入 | H2: 45000 | K2: ✈️出國旅遊專案 總支出(台幣)
A3: 46296 | B3: 一般花費 | C3: 支出 | D3: 電信費 | E3: 600 | F3: 🏦郵局 | G3: (自動) 範例固定扣款 | H3: 600 | I3: 一般花費 | K3: =SUMIFS('流水帳'!E:E, '流水帳'!C:C, "支出", '流水帳'!I:I, "✈️出國旅遊專案") -> 0
A4: 46300 | B4: 轉帳 | C4: 支出 | D4: 轉出至 👛錢包 | E4: 0 | F4: 🏦玉山生活 | G4: TWD 轉帳 | H4: 2000
A5: 46300 | B5: 轉帳 | C5: 收入 | D5: 來自 🏦玉山生活 轉入 | E5: 0 | F5: 👛錢包 | G5: TWD 轉帳 | H5: 2000
A6: 46315 | B6: 一般花費 | C6: 支出 | D6: 午餐 | E6: 150 | F6: 👛錢包 | G6: 範例一般支出 | H6: 150 | I6: 一般花費
A7: 46317 | B7: 特支費 | C7: 支出 | D7: 書籍/雜誌 | E7: 450 | F7: 💳富邦J卡 | G7: 範例特支消費 | H7: 450 | I7: 特支費

Sheet 月份查詢看板
A1: 請選擇年份 | B1: 2026 | C1: 請選擇月份 | D1: 10 | H1: 當月總支出 | I1: 當月總收入
H2: =SUMIFS('流水帳'!E:E, '流水帳'!C:C, "支出", '流水帳'!J:J, "<>代墊費", '流水帳'!A:A, ">="&DATE(B1,D1,1), '流水帳'!A:A, "<="&EOMONTH(DATE(B1,D1,1),0)) -> 1200 | I2: =SUMIFS('流水帳'!H:H, '流水帳'!A:A, ">="&DATE(B1,D1,1), '流水帳'!A:A, "<="&EOMONTH(DATE(B1,D1,1),0), '流水帳'!C:C, "收入", '流水帳'!B:B, "<>轉帳", '流水帳'!B:B, "<>餘額校準") -> 45000
A4: =IFERROR(__xludf.DUMMYFUNCTION("QUERY('流水帳'!A:H, ""SELECT * WHERE A IS NOT NULL AND YEAR(A) = "" & B1 & "" AND MONTH(A) = "" & (D1-1) & "" ORDER BY A DESC"", 1)"),"日期") -> 日期 | B4: =IFERROR(__xludf.DUMMYFUNCTION("""COMPUTED_VALUE"""),"類別") -> 類別 | C4: =IFERROR(__xludf.DUMMYFUNCTION("""COMPUTED_VALUE"""),"收支") -> 收支 | D4: =IFERROR(__xludf.DUMMYFUNCTION("""COMPUTED_VALUE"""),"項目") -> 項目 | E4: =IFERROR(__xludf.DUMMYFUNCTION("""COMPUTED_VALUE"""),"金額") -> 金額 | F4: =IFERROR(__xludf.DUMMYFUNCTION("""COMPUTED_VALUE"""),"帳戶/路徑") -> 帳戶/路徑 | G4: =IFERROR(__xludf.DUMMYFUNCTION("""COMPUTED_VALUE"""),"備註") -> 備註 | H4: =IFERROR(__xludf.DUMMYFUNCTION("""COMPUTED_VALUE"""),"H 原始金額 (必加)") -> H 原始金額 (必加) | J4: 日期 | K4: 當日總支出 | L4: 當日總收入
J5: {=SEQUENCE(DAY(EOMONTH(DATE(B1,D1,1),0)), 1, DATE(B1,D1,1))} -> 46296 | K5: {=MAP(J5:INDEX(J5:J1000, DAY(EOMONTH(DATE(B1,D1,1),0))), LAMBDA(d, SUMIFS('流水帳'!E:E, '流水帳'!A:A, d, '流水帳'!C:C, "支出")))} -> 600 | L5: {=MAP(J5:INDEX(J5:J1000, DAY(EOMONTH(DATE(B1,D1,1),0))), LAMBDA(d, SUMIFS('流水帳'!H:H, '流水帳'!A:A, d, '流水帳'!C:C, "收入", '流水帳'!B:B, "<>轉帳", '流水帳'!B:B, "<>餘額校準")))} -> 45000 | A5: =IFERROR(__xludf.DUMMYFUNCTION("""COMPUTED_VALUE"""),46317.0) -> 46317 | B5: =IFERROR(__xludf.DUMMYFUNCTION("""COMPUTED_VALUE"""),"特支費") -> 特支費 | C5: =IFERROR(__xludf.DUMMYFUNCTION("""COMPUTED_VALUE"""),"支出") -> 支出 | D5: =IFERROR(__xludf.DUMMYFUNCTION("""COMPUTED_VALUE"""),"書籍/雜誌") -> 書籍/雜誌 | E5: =IFERROR(__xludf.DUMMYFUNCTION("""COMPUTED_VALUE"""),450.0) -> 450 | F5: =IFERROR(__xludf.DUMMYFUNCTION("""COMPUTED_VALUE"""),"💳富邦J卡") -> 💳富邦J卡 | G5: =IFERROR(__xludf.DUMMYFUNCTION("""COMPUTED_VALUE"""),"範例特支消費") -> 範例特支消費 | H5: =IFERROR(__xludf.DUMMYFUNCTION("""COMPUTED_VALUE"""),450.0) -> 450
J6: 46297 | K6: 0 | L6: 0 | A6: =IFERROR(__xludf.DUMMYFUNCTION("""COMPUTED_VALUE"""),46315.0) -> 46315 | B6: =IFERROR(__xludf.DUMMYFUNCTION("""COMPUTED_VALUE"""),"一般花費") -> 一般花費 | C6: =IFERROR(__xludf.DUMMYFUNCTION("""COMPUTED_VALUE"""),"支出") -> 支出 | D6: =IFERROR(__xludf.DUMMYFUNCTION("""COMPUTED_VALUE"""),"午餐") -> 午餐 | E6: =IFERROR(__xludf.DUMMYFUNCTION("""COMPUTED_VALUE"""),150.0) -> 150 | F6: =IFERROR(__xludf.DUMMYFUNCTION("""COMPUTED_VALUE"""),"👛錢包") -> 👛錢包 | G6: =IFERROR(__xludf.DUMMYFUNCTION("""COMPUTED_VALUE"""),"範例一般支出") -> 範例一般支出 | H6: =IFERROR(__xludf.DUMMYFUNCTION("""COMPUTED_VALUE"""),150.0) -> 150
J7: 46298 | K7: 0 | L7: 0 | A7: =IFERROR(__xludf.DUMMYFUNCTION("""COMPUTED_VALUE"""),46300.0) -> 46300 | B7: =IFERROR(__xludf.DUMMYFUNCTION("""COMPUTED_VALUE"""),"轉帳") -> 轉帳 | C7: =IFERROR(__xludf.DUMMYFUNCTION("""COMPUTED_VALUE"""),"收入") -> 收入 | D7: =IFERROR(__xludf.DUMMYFUNCTION("""COMPUTED_VALUE"""),"來自 🏦玉山生活 轉入") -> 來自 🏦玉山生活 轉入 | E7: =IFERROR(__xludf.DUMMYFUNCTION("""COMPUTED_VALUE"""),0.0) -> 0 | F7: =IFERROR(__xludf.DUMMYFUNCTION("""COMPUTED_VALUE"""),"👛錢包") -> 👛錢包 | G7: =IFERROR(__xludf.DUMMYFUNCTION("""COMPUTED_VALUE"""),"TWD 轉帳") -> TWD 轉帳 | H7: =IFERROR(__xludf.DUMMYFUNCTION("""COMPUTED_VALUE"""),2000.0) -> 2000
J8: 46299 | K8: 0 | L8: 0 | A8: =IFERROR(__xludf.DUMMYFUNCTION("""COMPUTED_VALUE"""),46300.0) -> 46300 | B8: =IFERROR(__xludf.DUMMYFUNCTION("""COMPUTED_VALUE"""),"轉帳") -> 轉帳 | C8: =IFERROR(__xludf.DUMMYFUNCTION("""COMPUTED_VALUE"""),"支出") -> 支出 | D8: =IFERROR(__xludf.DUMMYFUNCTION("""COMPUTED_VALUE"""),"轉出至 👛錢包") -> 轉出至 👛錢包 | E8: =IFERROR(__xludf.DUMMYFUNCTION("""COMPUTED_VALUE"""),0.0) -> 0 | F8: =IFERROR(__xludf.DUMMYFUNCTION("""COMPUTED_VALUE"""),"🏦玉山生活") -> 🏦玉山生活 | G8: =IFERROR(__xludf.DUMMYFUNCTION("""COMPUTED_VALUE"""),"TWD 轉帳") -> TWD 轉帳 | H8: =IFERROR(__xludf.DUMMYFUNCTION("""COMPUTED_VALUE"""),2000.0) -> 2000
J9: 46300 | K9: 0 | L9: 0 | A9: =IFERROR(__xludf.DUMMYFUNCTION("""COMPUTED_VALUE"""),46296.0) -> 46296 | B9: =IFERROR(__xludf.DUMMYFUNCTION("""COMPUTED_VALUE"""),"一般花費") -> 一般花費 | C9: =IFERROR(__xludf.DUMMYFUNCTION("""COMPUTED_VALUE"""),"支出") -> 支出 | D9: =IFERROR(__xludf.DUMMYFUNCTION("""COMPUTED_VALUE"""),"電信費") -> 電信費 | E9: =IFERROR(__xludf.DUMMYFUNCTION("""COMPUTED_VALUE"""),600.0) -> 600 | F9: =IFERROR(__xludf.DUMMYFUNCTION("""COMPUTED_VALUE"""),"🏦郵局") -> 🏦郵局 | G9: =IFERROR(__xludf.DUMMYFUNCTION("""COMPUTED_VALUE"""),"(自動) 範例固定扣款") -> (自動) 範例固定扣款 | H9: =IFERROR(__xludf.DUMMYFUNCTION("""COMPUTED_VALUE"""),600.0) -> 600
J10: 46301 | K10: 0 | L10: 0 | A10: =IFERROR(__xludf.DUMMYFUNCTION("""COMPUTED_VALUE"""),46296.0) -> 46296 | B10: =IFERROR(__xludf.DUMMYFUNCTION("""COMPUTED_VALUE"""),"收入") -> 收入 | C10: =IFERROR(__xludf.DUMMYFUNCTION("""COMPUTED_VALUE"""),"收入") -> 收入 | D10: =IFERROR(__xludf.DUMMYFUNCTION("""COMPUTED_VALUE"""),"10月薪資 (範例)") -> 10月薪資 (範例) | E10: =IFERROR(__xludf.DUMMYFUNCTION("""COMPUTED_VALUE"""),0.0) -> 0 | F10: =IFERROR(__xludf.DUMMYFUNCTION("""COMPUTED_VALUE"""),"🏦玉山生活") -> 🏦玉山生活 | G10: =IFERROR(__xludf.DUMMYFUNCTION("""COMPUTED_VALUE"""),"TWD 收入") -> TWD 收入 | H10: =IFERROR(__xludf.DUMMYFUNCTION("""COMPUTED_VALUE"""),45000.0) -> 45000
J11: 46302 | K11: 0 | L11: 0
J12: 46303 | K12: 0 | L12: 0
J13: 46304 | K13: 0 | L13: 0
J14: 46305 | K14: 0 | L14: 0
J15: 46306 | K15: 0 | L15: 0
J16: 46307 | K16: 0 | L16: 0
J17: 46308 | K17: 0 | L17: 0
J18: 46309 | K18: 0 | L18: 0
J19: 46310 | K19: 0 | L19: 0
J20: 46311 | K20: 0 | L20: 0
J21: 46312 | K21: 0 | L21: 0
J22: 46313 | K22: 0 | L22: 0
... J35: 46326 | K35: 0 | L35: 0

Sheet 固定扣款設定
A1: A 項目名稱 | B1: B 類別 | C1: C 金額 | D1: D 幣別 | E1: E 扣款日期 (日) | F1: F 帳戶 | G1: G 備註 | H1: H 狀態 (啟用/停用)
A2: 定期保險 (範例) | B2: 一般花費 | C2: 2500 | D2: TWD | E2: 1 | F2: 💳富邦J卡 | H2: 啟用
A3: 電信費 | B3: 一般花費 | C3: 600 | D3: TWD | E3: 1 | F3: 🏦郵局 | H3: 啟用
A4: 健身房 | B4: 一般花費 | C4: 600 | D4: TWD | E4: 1 | F4: 💳富邦J卡 | H4: 啟用
A5: spotify | B5: 一般花費 | C5: 168 | D5: TWD | E5: 1 | F5: 💳富邦J卡 | H5: 啟用
A6: netflix | B6: 一般花費 | C6: 380 | D6: TWD | E6: 1 | F6: 💳富邦J卡 | H6: 啟用
A7: ChatGPT | B7: 一般花費 | C7: 690 | D7: TWD | E7: 1 | F7: 💳富邦J卡 | H7: 啟用

Sheet 每月金流規劃
A1: 收入 | D1: 一般支出 | J1: 其他 | M1: 支出總和
A2: 項目 | B2: 金額 | C2: 每月收入總計 | D2: 項目 | E2: 金額 | F2: 每月訂閱支出預算 | G2: 項目 | H2: 金額 | I2: 每月一般支出預算 | J2: 每年存20萬，每月要存 | K2: 一年出國預算4萬，每月存3300到專款基金 | M2: =F3+I3+J3+K3 -> 41548
A3: 薪資 | B3: 45000 | C3: =SUM(B3:B4) -> 50000 | D3: 定期保險 (範例) | E3: 2500 | F3: =SUM(E1:E18) -> 8248 | G3: 醫療保健預備 | H3: 600 | I3: =SUM(H3:H18) -> 13000 | J3: 17000 | K3: 3300
A4: 投資配息 | B4: 5000 | D4: 電信費 | E4: 600 | G4: 日常看診/藥品 | H4: 300
D5: 健身房 | E5: 600 | G5: 日常伙食 | H5: 10000
D6: spotify | E6: 168 | G6: 理髮/日用 | H6: 600
D7: 雲端/軟體訂閱 | E7: 600 | G7: 大眾運輸/悠遊卡 | H7: 1500
D8: 孝親費/家用 | E8: 3400
D9: Netflix | E9: 380
C20: 可使用金額(其他類) =每月收入-每月支出-每月要存
C21: =C3-M2 -> 8452
A23: 其他類預算
